y2m/__init__.py
y2m/py.typed
y2m/y2mconv.py
y2m/y2mlink.py
y2m/ytlive2m3u.py
y2m-0.4.dist-info/LICENSE
y2m-0.4.dist-info/METADATA
y2m-0.4.dist-info/WHEEL
y2m-0.4.dist-info/entry_points.txt
y2m-0.4.dist-info/top_level.txt
y2m-0.4.dist-info/RECORD
