Metadata-Version: 2.1
Name: y2m
Version: 0.4
Summary: Grab m3u from YouTube live
Home-page: UNKNOWN
Author: benmoose39
Author-email: unnik1998@gmail.com
Maintainer: eggplants
Maintainer-email: w10776e8w@yahoo.co.jp
License: MIT
Platform: UNKNOWN
Classifier: Programming Language :: Python :: 3.7
Classifier: Programming Language :: Python :: 3.8
Classifier: Programming Language :: Python :: 3.9
Classifier: Programming Language :: Python :: 3.10
Requires-Python: >=3.7
License-File: LICENSE
Provides-Extra: dev
Requires-Dist: black (>=21.12b0) ; extra == 'dev'
Requires-Dist: flake8 (>=4.0.1) ; extra == 'dev'
Requires-Dist: isort (>=5.10.1) ; extra == 'dev'
Requires-Dist: mypy (>=0.931) ; extra == 'dev'
Requires-Dist: types-setuptools (>=57.4.7) ; extra == 'dev'
